SoftExpertAPI/SoftExpertBaseAPI.py
SoftExpertAPI/SoftExpertException.py
SoftExpertAPI/SoftExpertOptions.py
SoftExpertAPI/SoftExpertWorkflowApi.py
SoftExpertAPI/__init__.py
softexpertapi-0.2.0.dist-info/METADATA
softexpertapi-0.2.0.dist-info/WHEEL
softexpertapi-0.2.0.dist-info/top_level.txt
softexpertapi-0.2.0.dist-info/RECORD
