Metadata-Version: 2.1
Name: SoftExpertAPI
Version: 0.2.0
Summary: Esta lib fornece um wrapper às APIs SoftExpert
Author-email: Gabriel Gontijo <gabrieldercilio08@gmail.com>, Hudson Ventura <hudsonventura@outlook.com>
Project-URL: Homepage, https://github.com/GGontijo/SoftExpertAPI
Project-URL: Bug Tracker, https://github.com/GGontijo/SoftExpertAPI/issues
Requires-Python: >=3.7
Requires-Dist: requests
